pem/__init__.py
pem/_compat.py
pem/_core.py
pem/py.typed
pem/twisted.py
pem-20.1.0.dist-info/AUTHORS.rst
pem-20.1.0.dist-info/LICENSE
pem-20.1.0.dist-info/METADATA
pem-20.1.0.dist-info/WHEEL
pem-20.1.0.dist-info/top_level.txt
pem-20.1.0.dist-info/RECORD
