Metadata-Version: 2.1
Name: pem
Version: 20.1.0
Summary: Easy PEM file parsing in Python.
Home-page: https://pem.readthedocs.io/
Author: Hynek Schlawack
Author-email: hs@ox.cx
Maintainer: Hynek Schlawack
Maintainer-email: hs@ox.cx
License: MIT
Project-URL: Documentation, https://pem.readthedocs.io/
Project-URL: Bug Tracker, https://github.com/hynek/pem/issues
Project-URL: Source Code, https://github.com/hynek/pem
Keywords: pyopenssl,ssl,tls,pem,cryptography,twisted
Platform: UNKNOWN
Classifier: Development Status :: 5 - Production/Stable
Classifier: Intended Audience :: Developers
Classifier: Natural Language :: English
Classifier: License :: OSI Approved :: MIT License
Classifier: Operating System :: OS Independent
Classifier: Programming Language :: Python
Classifier: Programming Language :: Python :: Implementation :: CPython
Classifier: Programming Language :: Python :: Implementation :: PyPy
Classifier: Programming Language :: Python :: 2
Classifier: Programming Language :: Python :: 2.7
Classifier: Programming Language :: Python :: 3
Classifier: Programming Language :: Python :: 3.5
Classifier: Programming Language :: Python :: 3.6
Classifier: Programming Language :: Python :: 3.7
Classifier: Programming Language :: Python :: 3.8
Classifier: Topic :: Software Development :: Libraries :: Python Modules
Provides-Extra: docs
Provides-Extra: tests
Provides-Extra: dev
Provides-Extra: azure-pipelines
